old_norse_alphabet/__init__.py
old_norse_alphabet/alphabet.py
old_norse_alphabet/sort.py
old_norse_alphabet-1.0.1.dist-info/LICENSE
old_norse_alphabet-1.0.1.dist-info/METADATA
old_norse_alphabet-1.0.1.dist-info/WHEEL
old_norse_alphabet-1.0.1.dist-info/top_level.txt
old_norse_alphabet-1.0.1.dist-info/RECORD
