Metadata-Version: 2.1
Name: old-norse-alphabet
Version: 1.0.1
Summary: Old Norse Alphabet & sorting
Home-page: https://github.com/stscoundrel/old-norse-alphabet-py
Author: stscoundrel
Requires-Python: >=3.9
License-File: LICENSE
